pycatenary/__init__.py
pycatenary/cable.py
pycatenary/catenary.py
pycatenary/root_finding.py
pycatenary/utils.py
pycatenary-1.0.0.dist-info/licenses/LICENSE
pycatenary-1.0.0.dist-info/METADATA
pycatenary-1.0.0.dist-info/WHEEL
pycatenary-1.0.0.dist-info/top_level.txt
pycatenary-1.0.0.dist-info/RECORD
