Metadata-Version: 2.4
Name: pycatenary
Version: 1.0.0
Summary: A Python library for solving catenary equations
Author-email: Tristan de Lataillade <delataillade.tristan@gmail.com>
Maintainer-email: Tristan de Lataillade <delataillade.tristan@gmail.com>
License-Expression: MIT
Project-URL: Homepage, https://github.com/tridelat/pycatenary
Project-URL: Repository, https://github.com/tridelat/pycatenary
Project-URL: Issues, https://github.com/tridelat/pycatenary/issues
Keywords: catenary,mooring,quasi-static,python
Classifier: Operating System :: OS Independent
Classifier: Programming Language :: Python :: 3
Classifier: Programming Language :: Python :: 3.9
Requires-Python: >=3.6
License-File: LICENSE
Requires-Dist: numpy>=1.16.0
Provides-Extra: plotting
Requires-Dist: matplotlib>=2.0.0; extra == "plotting"
Provides-Extra: dev
Requires-Dist: pytest>=6.0; extra == "dev"
Requires-Dist: black>=21.0; extra == "dev"
Requires-Dist: flake8>=3.8; extra == "dev"
Requires-Dist: isort>=5.0; extra == "dev"
Provides-Extra: docs
Requires-Dist: sphinx>=3.0; extra == "docs"
Requires-Dist: sphinx-rtd-theme>=0.5; extra == "docs"
Requires-Dist: myst-parser>=0.18; extra == "docs"
Dynamic: license-file
